squaretictactoe/__init__.py
squaretictactoe/square_tictactoe.css
squaretictactoe/square_tictactoe.py
squaretictactoe-1.6.0.dist-info/METADATA
squaretictactoe-1.6.0.dist-info/WHEEL
squaretictactoe-1.6.0.dist-info/entry_points.txt
squaretictactoe-1.6.0.dist-info/licenses/LICENSE
squaretictactoe-1.6.0.dist-info/RECORD
